kopfkino-0.1.3.dist-info/METADATA
kopfkino-0.1.3.dist-info/WHEEL
kopfkino-0.1.3.dist-info/entry_points.txt
kopfkino-0.1.3.dist-info/licenses/LICENSE
kopfkino/__init__.py
kopfkino/__main__.py
kopfkino/cli.py
kopfkino/py.typed
kopfkino-0.1.3.dist-info/RECORD
