Metadata-Version: 2.1
Name: kopfkino
Version: 0.1.3
Summary: Syntactic sugar sprinkled on top of MoviePy and AI components to allow authoring simple human-friendly video scripts.
Author-Email: Jürgen Hermann <jh@web.de>
License: Apache-2.0
Classifier: Development Status :: 4 - Beta
Classifier: Intended Audience :: Developers
Classifier: Programming Language :: Python
Classifier: Programming Language :: Python :: 3
Classifier: Programming Language :: Python :: 3 :: Only
Classifier: Programming Language :: Python :: 3.8
Classifier: Programming Language :: Python :: 3.9
Classifier: Programming Language :: Python :: 3.10
Classifier: Programming Language :: Python :: 3.11
Classifier: Programming Language :: Python :: 3.12
Classifier: Topic :: Documentation
Classifier: Topic :: Software Development
Classifier: Topic :: Utilities
Classifier: Typing :: Typed
Project-URL: Homepage, https://jhermann.github.io/kopfkino
Project-URL: Documentation, https://jhermann.github.io/kopfkino
Project-URL: Changelog, https://jhermann.github.io/kopfkino/changelog
Project-URL: Repository, https://github.com/jhermann/kopfkino
Project-URL: Issues, https://github.com/jhermann/kopfkino/issues
Project-URL: Discussions, https://github.com/jhermann/kopfkino/discussions
Project-URL: Gitter, https://gitter.im/kopfkino/community
Project-URL: Funding, https://github.com/sponsors/jhermann
Requires-Python: >=3.8
